LICENSE
MANIFEST.in
README.rst
setup.py
django_templatepages.egg-info/PKG-INFO
django_templatepages.egg-info/SOURCES.txt
django_templatepages.egg-info/dependency_links.txt
django_templatepages.egg-info/not-zip-safe
django_templatepages.egg-info/requires.txt
django_templatepages.egg-info/top_level.txt
templatepages/__init__.py
templatepages/middleware.py
templatepages/urls.py
templatepages/views.py