Metadata-Version: 1.1
Name: django-templatepages
Version: 0.2.2
Summary: Django app for mapping URLs to templates on the filesystem
Home-page: https://github.com/bryanchow/django-templatepages
Author: Bryan Chow
Author-email: UNKNOWN
License: BSD
Download-URL: https://github.com/bryanchow/django-templatepages/tarball/master
Platform: UNKNOWN
